<?xml version="1.0" encoding="UTF-8"?>
<install>
    <folders>${SYSTEM_CONF}/nginx</folders>
    <folders>${SYSTEM_CONF}/nginx/backup</folders>
    <folders>${SYSTEM_CONF}/nginx/working</folders>
    <copy_config>${SYSTEM_CONF}/nginx/parts</copy_config>
    <copy_config>${SYSTEM_CONF}/nginx/00_master.conf</copy_config>
    <copy_config>${SYSTEM_CONF}/nginx/00_master_ssl.conf</copy_config>
    <copy_config>${SYSTEM_CONF}/nginx/imscp_fastcgi.conf</copy_config>
    <copy_config>${SYSTEM_CONF}/nginx/imscp_php.conf</copy_config>
    <copy_config>${SYSTEM_CONF}/nginx/nginx.data</copy_config>
</install>
